pypast.py
pypast-0.0.1.dist-info/DESCRIPTION.rst
pypast-0.0.1.dist-info/METADATA
pypast-0.0.1.dist-info/RECORD
pypast-0.0.1.dist-info/WHEEL
pypast-0.0.1.dist-info/metadata.json
pypast-0.0.1.dist-info/top_level.txt
