Metadata-Version: 2.0
Name: pypast
Version: 0.0.1
Summary: Platform-Agnostic Security Tokens for Python
Home-page: https://github.com/JimDabell/pypast
Author: Jim Dabell
Author-email: UNKNOWN
License: UNKNOWN
Keywords: past security stateless tokens
Platform: UNKNOWN
Classifier: Development Status :: 1 - Planning
Classifier: Intended Audience :: Developers
Classifier: License :: OSI Approved :: MIT License
Classifier: Programming Language :: Python :: 3.6
Requires-Dist: libnacl (>=1.6.1)
